DynamoDBSQLLibrary/__init__.py
DynamoDBSQLLibrary/version.py
DynamoDBSQLLibrary/keywords/__init__.py
DynamoDBSQLLibrary/keywords/assertion.py
DynamoDBSQLLibrary/keywords/query.py
DynamoDBSQLLibrary/keywords/session.py
robotframework_dynamodbsqllibrary-0.3.1.dist-info/LICENSE
robotframework_dynamodbsqllibrary-0.3.1.dist-info/METADATA
robotframework_dynamodbsqllibrary-0.3.1.dist-info/WHEEL
robotframework_dynamodbsqllibrary-0.3.1.dist-info/top_level.txt
robotframework_dynamodbsqllibrary-0.3.1.dist-info/RECORD
