Metadata-Version: 2.1
Name: robotframework-dynamodbsqllibrary
Version: 0.3.1
Summary: An Amazon AWS DynamoDB big data testing library for Robot Framework with SQL-like DSL
Home-page: https://github.com/rickypc/robotframework-dynamodbsqllibrary
Author: Richard Huang
Author-email: rickypc@users.noreply.github.com
License: AGPL 3
Keywords: robot framework testing automation bigdata amazon dynamodb dynamo db nosql sql dsl json aws big data softwaretesting
Platform: any
Classifier: Development Status :: 4 - Beta
Classifier: Framework :: Robot Framework
Classifier: Intended Audience :: Developers
Classifier: License :: OSI Approved :: GNU Affero General Public License v3
Classifier: Natural Language :: English
Classifier: Programming Language :: Python :: 3
Classifier: Topic :: Software Development :: Testing
Requires-Python: <3.10,>=3.6
License-File: LICENSE
Requires-Dist: boto3 (>=1.16.15)
Requires-Dist: dql (>=0.5.28)
Requires-Dist: robotframework (>=3.0)
